{
	"color": {
		"name": "Unknown",
		"space": "RGB",
		"firstField": 0.000000,
		"secondField": 0.000000,
		"thirdField": 0.000000
	},
	"numberOfLayers": 1,
	"layer": {
		"number": 1,
		"fillingType": "Simple Fill",
		"lineProperties": {
			"name": "Outline",
			"type": "Cartographic Line",
			"lineCaps": "Square",
			"lineJoins": "Round",
			"width": 3.000000,
			"propertiesOffset": 3.000000,
			"color": {
				"name": "Line Color",
				"space": "CMYK",
				"C": 4,
				"M": 34,
				"Y": 70,
				"K": 23
			},
			"template": {
				"interval": 2.000000,
			}
		},
		"color": {
			"name": "Filling Color",
			"space": "RGB",
			"firstField": 0.000000,
			"secondField": 0.000000,
			"thirdField": 0.000000
		},
	},
}
